noterm/__init__.py
noterm/alert_ex.js
noterm/consolestyle.js
noterm/htsv.py
noterm/movefiler.py
noterm/reqbasher.py
noterm/srvrun.py
noterm/tabletemplate.html
noterm-0.0.7.dist-info/LICENSE
noterm-0.0.7.dist-info/METADATA
noterm-0.0.7.dist-info/WHEEL
noterm-0.0.7.dist-info/entry_points.txt
noterm-0.0.7.dist-info/top_level.txt
noterm-0.0.7.dist-info/RECORD
